clipstream/.mypy_cache/.gitignore
clipstream/.mypy_cache/3.10/@plugins_snapshot.json
clipstream/.mypy_cache/3.10/_ast.data.json
clipstream/.mypy_cache/3.10/_ast.meta.json
clipstream/.mypy_cache/3.10/_codecs.data.json
clipstream/.mypy_cache/3.10/_codecs.meta.json
clipstream/.mypy_cache/3.10/_collections_abc.data.json
clipstream/.mypy_cache/3.10/_collections_abc.meta.json
clipstream/.mypy_cache/3.10/_ctypes.data.json
clipstream/.mypy_cache/3.10/_ctypes.meta.json
clipstream/.mypy_cache/3.10/_socket.data.json
clipstream/.mypy_cache/3.10/_socket.meta.json
clipstream/.mypy_cache/3.10/_thread.data.json
clipstream/.mypy_cache/3.10/_thread.meta.json
clipstream/.mypy_cache/3.10/_typeshed/__init__.data.json
clipstream/.mypy_cache/3.10/_typeshed/__init__.meta.json
clipstream/.mypy_cache/3.10/_weakref.data.json
clipstream/.mypy_cache/3.10/_weakref.meta.json
clipstream/.mypy_cache/3.10/_weakrefset.data.json
clipstream/.mypy_cache/3.10/_weakrefset.meta.json
clipstream/.mypy_cache/3.10/abc.data.json
clipstream/.mypy_cache/3.10/abc.meta.json
clipstream/.mypy_cache/3.10/argparse.data.json
clipstream/.mypy_cache/3.10/argparse.meta.json
clipstream/.mypy_cache/3.10/array.data.json
clipstream/.mypy_cache/3.10/array.meta.json
clipstream/.mypy_cache/3.10/asyncio/__init__.data.json
clipstream/.mypy_cache/3.10/asyncio/__init__.meta.json
clipstream/.mypy_cache/3.10/asyncio/base_events.data.json
clipstream/.mypy_cache/3.10/asyncio/base_events.meta.json
clipstream/.mypy_cache/3.10/asyncio/coroutines.data.json
clipstream/.mypy_cache/3.10/asyncio/coroutines.meta.json
clipstream/.mypy_cache/3.10/asyncio/events.data.json
clipstream/.mypy_cache/3.10/asyncio/events.meta.json
clipstream/.mypy_cache/3.10/asyncio/exceptions.data.json
clipstream/.mypy_cache/3.10/asyncio/exceptions.meta.json
clipstream/.mypy_cache/3.10/asyncio/futures.data.json
clipstream/.mypy_cache/3.10/asyncio/futures.meta.json
clipstream/.mypy_cache/3.10/asyncio/locks.data.json
clipstream/.mypy_cache/3.10/asyncio/locks.meta.json
clipstream-0.1.0.dist-info/METADATA
clipstream-0.1.0.dist-info/WHEEL
clipstream-0.1.0.dist-info/entry_points.txt
clipstream-0.1.0.dist-info/RECORD
