Metadata-Version: 2.1
Name: clipstream
Version: 0.1.0
Summary: 
Author: Pedro Batista
Author-email: pedrovhb@gmail.com
Requires-Python: >=3.10,<4.0
Classifier: Programming Language :: Python :: 3
Classifier: Programming Language :: Python :: 3.10
Classifier: Programming Language :: Python :: 3.11
Requires-Dist: asynkets (>=0.1.0,<0.2.0)
Requires-Dist: pyperclip (>=1.8.2,<2.0.0)
Requires-Dist: python-xlib (>=0.33,<0.34)
